{
    "Type":"Neutral",
            "Dev comment":" Sup increases self speed.",
            "Dev comment":" Dup increases self defense.",
    "Actions":[
        {

            "If":{
                "Type":"Random",
                "Chance":0.30,
                "Then":[
                    {
                        "Apply Effect":
                        {
                            "Target":"Self",
                            "Effect":{
                                "Hup":0.10,
                                "Pup":0.04,
                                "Sup":0.02,
                                "Dup":0.08
                        }}
                    },
                    {
                        
                    }
                ]
            }
        }
        
    ]
}
